simple_signal_bot/__init__.py
simple_signal_bot/signal_bot.py
simple_signal_bot/decorator/__init__.py
simple_signal_bot/decorator/command_decorator.py
simple_signal_bot/decorator/message_decorator.py
simple_signal_bot/manager/__init__.py
simple_signal_bot/manager/regex_manager.py
simple_signal_bot/model/__init__.py
simple_signal_bot/model/source_information.py
simple_signal_bot/signal_io/__init__.py
simple_signal_bot/signal_io/receiver.py
simple_signal_bot/signal_io/sender.py
simple_signal_bot/util/__init__.py
simple_signal_bot/util/constants.py
simple_signal_bot/util/context.py
simple_signal_bot/util/envelope_utils.py
simple_signal_bot/util/group_utils.py
simple_signal_bot/util/regex.py
simple_signal_bot-1.0.4.dist-info/METADATA
simple_signal_bot-1.0.4.dist-info/WHEEL
simple_signal_bot-1.0.4.dist-info/licenses/LICENSE
simple_signal_bot-1.0.4.dist-info/RECORD
