Metadata-Version: 2.1
Name: simple-signal-bot
Version: 1.0.4
Summary: Einfacher Signal Bot der mit einer REST API (bbernhard/signal-cli-rest-api) interagiert
Project-URL: Homepage, https://github.com/baspla/signal_bot
Author-email: Baspla <pydev@mailbox.org>
License: MIT License
Keywords: bot,signal
Classifier: Programming Language :: Python
Classifier: Programming Language :: Python :: 3
Requires-Python: >=3.7
Requires-Dist: requests>=2.28.1
Requires-Dist: timeloop>=1.0.2
